rss3_dsl_sdk/__init__.py
rss3_dsl_sdk/client.py
rss3_dsl_sdk/schemas/__init__.py
rss3_dsl_sdk/schemas/base.py
rss3_dsl_sdk/schemas/collectible.py
rss3_dsl_sdk/schemas/enums.py
rss3_dsl_sdk/schemas/exchange.py
rss3_dsl_sdk/schemas/metaverse.py
rss3_dsl_sdk/schemas/rss.py
rss3_dsl_sdk/schemas/social.py
rss3_dsl_sdk/schemas/transaction.py
rss3_dsl_sdk-0.4.0.dist-info/LICENSE
rss3_dsl_sdk-0.4.0.dist-info/METADATA
rss3_dsl_sdk-0.4.0.dist-info/WHEEL
rss3_dsl_sdk-0.4.0.dist-info/RECORD
