Metadata-Version: 2.1
Name: rss3-dsl-sdk
Version: 0.4.0
Summary: A Python SDK for RSS3 Data Sub Layer (DSL)
Author: Your Name
Author-email: your.email@example.com
Requires-Python: >=3.9,<4.0
Classifier: Programming Language :: Python :: 3
Classifier: Programming Language :: Python :: 3.9
Classifier: Programming Language :: Python :: 3.10
Classifier: Programming Language :: Python :: 3.11
Classifier: Programming Language :: Python :: 3.12
Requires-Dist: pydantic (>=2.8.2,<3.0.0)
Requires-Dist: requests (>=2.32.3,<3.0.0)
